setup.py
analogbridge/__init__.py
analogbridge/api_request.py
analogbridge/resource.py
analogbridge.egg-info/PKG-INFO
analogbridge.egg-info/SOURCES.txt
analogbridge.egg-info/dependency_links.txt
analogbridge.egg-info/requires.txt
analogbridge.egg-info/top_level.txt